{
  "generator-jhipster": {
    "promptValues": {
      "packageName": "com.mycompany.myapp"
    },
    "jhipsterVersion": "6.5.0",
    "applicationType": "monolith",
    "baseName": "kafka",
    "packageName": "com.mycompany.myapp",
    "packageFolder": "com/mycompany/myapp",
    "serverPort": "8080",
    "authenticationType": "jwt",
    "cacheProvider": "no",
    "enableHibernateCache": false,
    "websocket": false,
    "databaseType": "no",
    "devDatabaseType": "no",
    "prodDatabaseType": "no",
    "searchEngine": false,
    "messageBroker": "kafka",
    "serviceDiscoveryType": false,
    "buildTool": "maven",
    "enableSwaggerCodegen": false,
    "jwtSecretKey": "YWM4ZTQ1YTcwZGFhNWFhY2RiODZlYzA3ZTA5NzhjOGEyZjNlNmNlYmI0OTQ5N2ZkYzgzMmEwZjI2NDRjM2JmZGJmMTQyYmU2OTI5ZjU1MTQ1MjkzNWI1MWZjNzQzNzg5MDI2NWI0MDdhMTEwNTUxOGU5ODc3NjFiNGQ5NzZmYjc=",
    "embeddableLaunchScript": false,
    "useSass": true,
    "clientPackageManager": "npm",
    "skipClient": true,
    "testFrameworks": [],
    "jhiPrefix": "jhi",
    "entitySuffix": "",
    "dtoSuffix": "DTO",
    "otherModules": [],
    "enableTranslation": false,
    "blueprints": []
  }
}